novograd/__init__.py
novograd/novograd.py
novograd-0.0.1.dist-info/METADATA
novograd-0.0.1.dist-info/RECORD
novograd-0.0.1.dist-info/WHEEL
novograd-0.0.1.dist-info/top_level.txt
